pipenv_to_requirements/__init__.py
pipenv_to_requirements/test_cli.py
pipenv_to_requirements/test_parsing.py
pipenv_to_requirements/vectors/Pipfile.editable
pipenv_to_requirements/vectors/Pipfile.editable.requirements-dev.txt
pipenv_to_requirements/vectors/Pipfile.editable.requirements.txt
pipenv_to_requirements/vectors/Pipfile.extras
pipenv_to_requirements/vectors/Pipfile.extras.requirements-dev.txt
pipenv_to_requirements/vectors/Pipfile.extras.requirements.txt
pipenv_to_requirements/vectors/Pipfile.markers
pipenv_to_requirements/vectors/Pipfile.markers.requirements-dev.txt
pipenv_to_requirements/vectors/Pipfile.markers.requirements.txt
pipenv_to_requirements/vectors/Pipfile.normal
pipenv_to_requirements/vectors/Pipfile.normal.requirements-dev.txt
pipenv_to_requirements/vectors/Pipfile.normal.requirements.txt
pipenv_to_requirements-0.9.0.dist-info/AUTHORS
pipenv_to_requirements-0.9.0.dist-info/LICENSE
pipenv_to_requirements-0.9.0.dist-info/METADATA
pipenv_to_requirements-0.9.0.dist-info/WHEEL
pipenv_to_requirements-0.9.0.dist-info/entry_points.txt
pipenv_to_requirements-0.9.0.dist-info/pbr.json
pipenv_to_requirements-0.9.0.dist-info/top_level.txt
pipenv_to_requirements-0.9.0.dist-info/RECORD
