Metadata-Version: 1.1
Name: pipenv-to-requirements
Version: 0.9.0
Summary: Generate requirements[-dev].txt from Pipfile using pipenv
Home-page: https://github.com/gsemet/pipenv-to-requirements
Author: Gaetan Semet
Author-email: gaetan@xeberon.net
License: UNKNOWN
Platform: UNKNOWN
Classifier: Intended Audience :: Information Technology
Classifier: Intended Audience :: System Administrators
Classifier: License :: OSI Approved :: MIT License
Classifier: Operating System :: POSIX :: Linux
Classifier: Programming Language :: Python
Classifier: Programming Language :: Python :: 3
Classifier: Programming Language :: Python :: 3.6
Classifier: Programming Language :: Python :: 3.7
